<?xml version="1.0" encoding="utf-8"?>
<index>
	<info>
		<name>Me</name>
		<description>The Me is Me.</description>
		<author url="https://example.com">Me</author>
		<update version="0.0.1">
			<file name="background-field_medic.index" url="https://raw.githubusercontent.com/animalsandsuch/cuddly-octo-doodle/main/background-field_medic.index" />
		</update>
	</info>
	<files>	
		<file name="sources.xml" url="https://raw.githubusercontent.com/animalsandsuch/cuddly-octo-doodle/main/sources.xml" />
		<!-- backgrounds -->		
		<file name="background-field_medic.xml" url="https://raw.githubusercontent.com/animalsandsuch/cuddly-octo-doodle/main/background-field_medic.xml" />
	</files>
</index>